{
  "kind": "collectionType",
  "collectionName": "classrooms",
  "info": {
    "singularName": "classroom",
    "pluralName": "classrooms",
    "displayName": "Classroom",
    "description": ""
  },
  "options": {
    "draftAndPublish": true
  },
  "pluginOptions": {},
  "attributes": {
    "students": {
      "type": "relation",
      "relation": "manyToMany",
      "target": "api::student.student",
      "inversedBy": "classrooms"
    },
    "teachers": {
      "type": "relation",
      "relation": "manyToMany",
      "target": "api::teacher.teacher",
      "inversedBy": "classrooms"
    },
    "subjects": {
      "type": "relation",
      "relation": "manyToMany",
      "target": "api::subject.subject",
      "inversedBy": "classrooms"
    },
    "ClassName": {
      "type": "string",
      "required": true
    },
    "rooms": {
      "type": "relation",
      "relation": "manyToMany",
      "target": "api::room.room",
      "inversedBy": "classrooms"
    }
  }
}
